{"title":"Mac_OS_X Lion_10.7_VMware_Pre-Installed_Image","uid":7547071,"size":4640381293,"categoryP":"applications","categoryS":"mac","magnet":"?xt=urn:btih:14b6f733de53d47e1585c00d788c474b789db447&amp;dn=Mac_OS_X+Lion_10.7_VMware_Pre-Installed_Image&amp;tr=udp%3A%2F%2Ftracker.openbittorrent.com%3A80&amp;tr=udp%3A%2F%2Fopen.demonii.com%3A1337&amp;tr=udp%3A%2F%2Ftracker.coppersurfer.tk%3A6969&amp;tr=udp%3A%2F%2Fexodus.desync.com%3A6969","seeders":1,"leechers":0,"uploader":"sspenser","files":1,"time":1345377514,"description":"Mac OS X Lion 10.7 VMware","torrent":{"xt":"urn:btih:14b6f733de53d47e1585c00d788c474b789db447","amp;dn":"Mac_OS_X+Lion_10.7_VMware_Pre-Installed_Image","amp;tr":["udp%3A%2F%2Ftracker.openbittorrent.com%3A80","udp%3A%2F%2Fopen.demonii.com%3A1337","udp%3A%2F%2Ftracker.coppersurfer.tk%3A6969","udp%3A%2F%2Fexodus.desync.com%3A6969"],"infoHash":"14b6f733de53d47e1585c00d788c474b789db447","infoHashBuffer":{"type":"Buffer","data":[20,182,247,51,222,83,212,126,21,133,192,13,120,140,71,75,120,157,180,71]},"announce":[],"urlList":[]}}