{"title":"Casa Mickey - 30 Sir Goofy [DVDRip][Spanish]","uid":6616773,"size":228141292,"categoryP":"video","categoryS":"movies","magnet":"?xt=urn:btih:17eebeb8f8cd541109da9d8fe91ca8150bbf1c96&amp;dn=Casa+Mickey+-+30+Sir+Goofy+%5BDVDRip%5D%5BSpanish%5D&amp;tr=udp%3A%2F%2Ftracker.openbittorrent.com%3A80&amp;tr=udp%3A%2F%2Fopen.demonii.com%3A1337&amp;tr=udp%3A%2F%2Ftracker.coppersurfer.tk%3A6969&amp;tr=udp%3A%2F%2Fexodus.desync.com%3A6969","seeders":1,"leechers":0,"uploader":"virana","files":-1,"time":1313828013,"description":"Casa de Mickey - Sir Goofy","torrent":{"xt":"urn:btih:17eebeb8f8cd541109da9d8fe91ca8150bbf1c96","amp;dn":"Casa+Mickey+-+30+Sir+Goofy+%5BDVDRip%5D%5BSpanish%5D","amp;tr":["udp%3A%2F%2Ftracker.openbittorrent.com%3A80","udp%3A%2F%2Fopen.demonii.com%3A1337","udp%3A%2F%2Ftracker.coppersurfer.tk%3A6969","udp%3A%2F%2Fexodus.desync.com%3A6969"],"infoHash":"17eebeb8f8cd541109da9d8fe91ca8150bbf1c96","infoHashBuffer":{"type":"Buffer","data":[23,238,190,184,248,205,84,17,9,218,157,143,233,28,168,21,11,191,28,150]},"announce":[],"urlList":[]}}