{"title":"Ali Campbell - Running Free [2007] @ 192kbps [REGGAE]","uid":5575875,"size":75725736,"categoryP":"audio","categoryS":"music","magnet":"?xt=urn:btih:2122b663fa77d2910778edfe9871d666599b93e0&amp;dn=Ali+Campbell+-+Running+Free+%5B2007%5D+%40+192kbps+%5BREGGAE%5D&amp;tr=udp%3A%2F%2Ftracker.openbittorrent.com%3A80&amp;tr=udp%3A%2F%2Fopen.demonii.com%3A1337&amp;tr=udp%3A%2F%2Ftracker.coppersurfer.tk%3A6969&amp;tr=udp%3A%2F%2Fexodus.desync.com%3A6969","seeders":1,"leechers":0,"uploader":"tourizmo","files":-1,"time":1274383215,"description":"Ali Campbell - Running Free 2007\n\n[192kbps MP3]\n\n\n\n1.  Running Free - Ali Campbell, Beverley Knight \n\t\n2.  Hold Me Tight - Ali Campbell \t\n\n3.  I'll Be Standing By - Ali Campbell, Lemar \t\n\n4.  Don't Go - Ali Campbell \t\n\n5.  Would I Lie to You - Ali Campbell, Bitty McLean \n\t\n6.  I Want One of Those - Ali Campbell \t\n\n7.  Hallelujah Time - Ali Campbell, Smokey Robinson \t\n\n8.  Don't Try This at Home - Ali Campbell, Katie Melua \t\n\n9.  Flex - Ali Campbell \t\n\n10. Being with You - Ali Campbell, Mick Hucknall \n\t\n11. Gotta Get Away - Ali Campbell \t\n\n12. Devoted to You - Ali Campbell, Robin Campbell \t\n\n13. Village Ghetto Land - Aston Barrett, Aston Barrett, Ali Campbell, Don Yute\n \t\n14. Cold Around My Heart - Ali Campbell \n\n*ENJOY*\n\n\n                                 .. .... ..                                     \n                                  .....  ...                                    \n                                  .. .MM: .  .                                  \n                                .. . .7M7.~7....                                \n                                 .....:8MMMM=. .                                \n                    .               IMMMMM~ . ..                                \n                 ...................,I~:NMZ,........      .  . .                \n       .         .. ....   ............ ZMMZ ........      .                    \n                .. .78888888OOI+.........,NMZZ7+.  .              .             \n  ..................?DOOOOO8OOOO88?:......=NN?O8~ ...      .. +=?,...           \n  ... ....:+ZO888O7?$O$IIII7$$OO8O888O+:...+MN88O....      .. IM7 . .           \n.. ...788OZOOOOOOOOOZ$$ZZ$$$$$I7??I7OO8O88D8O888$.....     . DMMMM8..           \n. ..,I+:... +???????$$$$$$$$$$$$ZZ77??I7ZOOOOO$77.....     ... ? .  .           \n..........~I$$$Z$$$$$$$ZZZZZZZZ$$$$$ZZ$7I?II7$Z$,.. .... ,     7. . . .. .      \n ......=ZZZ$7IIIZZZ$$$?.... .  ..:+?$ZZZZZZZ$++MD.. ..  . DN8MMMMMZDMZ ...      \n .....=?:.........,~ZZ: ...............,.:,, ..=MO....  . .ONONMMDMM? . ..      \n.    ....  .. .  ........... . ........ .. .....MM. . .. . ~8D8ZZNOO... .       \n                    . +=  . ZZ+=. ..    . .. . ..8D.. .  ,+DMMMNNMMM: . .       \n                   . . ,ON88NMMMMM . .       ..  ,M8 .:OMDNMMN7DIOMN?.....      \n .........  ...   . .. .,7MMMMMMMMN~..     .... ..=MMMO8MMMMD7DODO.~..?~  . . . \n  ... ,=ODDDNDOZ?~..  ..=ZMNZ?,,MMN+..     .    .+MMM8MMMMDDMMMD77 =MN8+,..     \n.  .:$:  ..,:,:,. :ZDZ:, .   ...MM7 . .    .  ,IMMMDMMMMM8DMMMNDD7 ..7MM=?....  \n  ,$  +O+..  .      :+I$$ONNMMMN=. .. ... ,7MMMMMNMMMMMMNMMMMMMMDO:. .MI:Z+I... \n. +=.?~  ......... .      .::.  ... ...  :MMMMMMMMMMMMMMMMO8MMMMMN7~  M7?IMM..  \n  I ,Z  ....  .  .=?I$OO$7?+=~~~~~~==+IINMMMO=DMMMMMN+. ~$MMZDMMMM?~ .MN?=MO  . \n  ?O. +Z+,  ~~+,.   ...         .,,,...   I: ,M?7. ... . . :MMOMMMMM. ~ D8  ... \n  .~:   ,~+=, .,?I..... .         .     ..  .D  .  .   .  . ~NOMMMMMMMMZN8      \n  ..:IDO?+I7ODMMMD,. ..                 .. ..,. . .       .. $MMMMMMM$.=?,      \n . .    ..,:::MM. .   .               .. . ..    . ..     . . M8MNMMM8N7 .      \n        . .. ~N,                          .     . $$      .. .MMMOMM=  .        \n       .... ~NI.. .    .      .          .       .M+ .    . . MMMZMM:           \n        ....NM....      .                    .  .Z= ..    .  =MMMMMM.           \n       . .. MM .  ..    ..  ... .. ..  .... ....DM. .     ..,DMMMMMD.           \n       .    MO   .. ... .:+=~~,.    ....  :~~+88M$  .     . MMMMMMM?.           \n     . . . :M:   . . .?NMMMM+:?$DMMD$$77DMMMMMMMMM  .      ~MMMMZI...           \n   . .  . :N:.. . .  +MMMMMM$.   .,=$OMMMMMMMMMMMMO:.. .  . MMMM  .    .        \n  ...  . =O,.  ..  .MMMMMMMMM~ ...  :?7ZMDNMMMMMMMMMMZ  .  ..O,ZN,.. .....      \n    ..  8M. ..    +$ ,MMMMMMM+ .  ..  ., :::7?:IMMMMMMN7    . +?MO,=:~, ..      \n     .NM~. . .  ~Z: ..?MMMMMM+   . ........  . $MMMMMNMM8~ . ...~:,.  ....      \n .  MN......~Z$:..     7MMMMM+   .    .    . .DMMMMM. MDMONO  .   .    ,+=      \n   .DM:   ZN.....    ..7MMMMM?  . .         .,MMMMM8  D~8, :MMMMMD..  $$MD      \n  . OM  .Z,.. ....   ..7$MMMMI .  .        .~NMMMM8,. + I    =+..IMMMO8MM=      \n  . N8. 8I .           ~OMMMMM,.. ..      . MMMMMM..... ..      ...,MM8=        \n    MZ. 8I ..         .. ZNMMMMI ...       .NMMMMM ..  .. .     ... ZN  ..      \n . .MZ  ON.            .. ZIMMMM+  . .     ,N?MMMN  ......      . ...$~         \n    MN  . .8MO ..         .  OMMMMMMDO. ...  .MMMM$$:  . .      .    .MI.       \n  . NM  =$ Z:8.  .         . +MMM8=8 =,... . =MMMO8M+: .         . . .7M .      \n  . =MMMO+DMMM. ..           .MMMMNIMZ? ......MMMM$MO7 . .           . 7?       \n   .                             .       .    .        .                        \n.            .              .   . .      .         ..                    .      \n             ..               .   .          .    .   .                         \n\n\n\n\n","torrent":{"xt":"urn:btih:2122b663fa77d2910778edfe9871d666599b93e0","amp;dn":"Ali+Campbell+-+Running+Free+%5B2007%5D+%40+192kbps+%5BREGGAE%5D","amp;tr":["udp%3A%2F%2Ftracker.openbittorrent.com%3A80","udp%3A%2F%2Fopen.demonii.com%3A1337","udp%3A%2F%2Ftracker.coppersurfer.tk%3A6969","udp%3A%2F%2Fexodus.desync.com%3A6969"],"infoHash":"2122b663fa77d2910778edfe9871d666599b93e0","infoHashBuffer":{"type":"Buffer","data":[33,34,182,99,250,119,210,145,7,120,237,254,152,113,214,102,89,155,147,224]},"announce":[],"urlList":[]}}