{"title":"The Dirty Picture (2011) Hindi 1CD DVDRip x264 AAC xDM","uid":6967493,"size":729135846,"categoryP":"video","categoryS":"movies","magnet":"?xt=urn:btih:2c0ef6384e79187da96a75057a447eecc7ae0922&amp;dn=The+Dirty+Picture+%282011%29+Hindi+1CD+DVDRip+x264+AAC+xDM&amp;tr=udp%3A%2F%2Ftracker.openbittorrent.com%3A80&amp;tr=udp%3A%2F%2Fopen.demonii.com%3A1337&amp;tr=udp%3A%2F%2Ftracker.coppersurfer.tk%3A6969&amp;tr=udp%3A%2F%2Fexodus.desync.com%3A6969","seeders":1,"leechers":0,"uploader":"HDvideos","files":-1,"time":1326931885,"description":"mastitorrents.com\n &lt;a href=&quot;\nhttp://mastitorrents.com/forums/index.php&quot; rel=&quot;nofollow&quot; target=&quot;_NEW&quot;&gt;\nhttp://mastitorrents.com/forums/index.php&lt;/a&gt;\n &lt;a href=&quot;\nhttp://thepiratebay.se/user/HDvideos/0/7&quot; rel=&quot;nofollow&quot; target=&quot;_NEW&quot;&gt;\nhttp://thepiratebay.se/user/HDvideos/0/7&lt;/a&gt;\n\nThe Dirty Picture (2011) Hindi 1CD DVDRip x264 AAC xDM@Mastitorrents\n\nSource..............: DVD9 @ xDM\nRipper..............: xDM Ripper\nRelease Date........: Who Cares?\nSize................: 696 MiB\nFrame Rate..........: 29.xx fps\nRuntime.............: 2 Hr 29Mins\nVideo Codec.........: x264\nVideo Bitrate.......: 628 KBPS\nAudio Info..........: AAC 48Kbps\nContainer...........: MKV\nResolution..........: 608 x 272\nAudio Language......: Hindi\nSubs................: N/A\n\nRip Highlights......: \nEnjoY the Quality\nScreens Taken From Rip Not From Script\nCheck SamPLe For Quality\n\nRipper Notes........:\nEnjoY the Quality Release From xDM","torrent":{"xt":"urn:btih:2c0ef6384e79187da96a75057a447eecc7ae0922","amp;dn":"The+Dirty+Picture+%282011%29+Hindi+1CD+DVDRip+x264+AAC+xDM","amp;tr":["udp%3A%2F%2Ftracker.openbittorrent.com%3A80","udp%3A%2F%2Fopen.demonii.com%3A1337","udp%3A%2F%2Ftracker.coppersurfer.tk%3A6969","udp%3A%2F%2Fexodus.desync.com%3A6969"],"infoHash":"2c0ef6384e79187da96a75057a447eecc7ae0922","infoHashBuffer":{"type":"Buffer","data":[44,14,246,56,78,121,24,125,169,106,117,5,122,68,126,236,199,174,9,34]},"announce":[],"urlList":[]}}