{"title":"Researching the Future in Information Systems","uid":6537158,"size":2428996,"categoryP":"other","categoryS":"e_books","magnet":"?xt=urn:btih:3b3081cda449432d802c4894f2332f38e567ad4a&amp;dn=Researching+the+Future+in+Information+Systems&amp;tr=udp%3A%2F%2Ftracker.openbittorrent.com%3A80&amp;tr=udp%3A%2F%2Fopen.demonii.com%3A1337&amp;tr=udp%3A%2F%2Ftracker.coppersurfer.tk%3A6969&amp;tr=udp%3A%2F%2Fexodus.desync.com%3A6969","seeders":1,"leechers":0,"uploader":"_F1_","files":-1,"time":1310555007,"description":"Mike Chiasson, Ola Henfridsson, Helena Karsten, Janice I. DeGross, &quot;Researching the Future in Information Systems&quot; \n Sp,..er | 2011 | ISBN: 3642213634 | 328 pages | PDF | 2.31 MB \n\n This book constitutes the refereed proceedings of the IFIP WG 8.2 Working Conference &quot;Researching the Future&quot;, Future IS 2011, held in Turku, Finland, in June 2011. The 17 revised full papers presented together with 4 panels and workshops were carefully reviewed and selected from numerous submissions. The papers are organized into 6 topical sections: how the future and the past are connected and inter-related; critical view of the future; technological futures; the future of information technology and work-related practices in health care; the future of industrial and institutional practices and outcomes through information technology; and the future of critical realism in IS research.","torrent":{"xt":"urn:btih:3b3081cda449432d802c4894f2332f38e567ad4a","amp;dn":"Researching+the+Future+in+Information+Systems","amp;tr":["udp%3A%2F%2Ftracker.openbittorrent.com%3A80","udp%3A%2F%2Fopen.demonii.com%3A1337","udp%3A%2F%2Ftracker.coppersurfer.tk%3A6969","udp%3A%2F%2Fexodus.desync.com%3A6969"],"infoHash":"3b3081cda449432d802c4894f2332f38e567ad4a","infoHashBuffer":{"type":"Buffer","data":[59,48,129,205,164,73,67,45,128,44,72,148,242,51,47,56,229,103,173,74]},"announce":[],"urlList":[]}}