{"title":"Lyzanxia - Locust (2010) [mp3@320]","uid":5922755,"size":115814716,"categoryP":"audio","categoryS":"music","magnet":"?xt=urn:btih:48be611c499aad9b5830f78b58a2730b7f237dff&amp;dn=Lyzanxia+-+Locust+%282010%29+%5Bmp3%40320%5D&amp;tr=udp%3A%2F%2Ftracker.openbittorrent.com%3A80&amp;tr=udp%3A%2F%2Fopen.demonii.com%3A1337&amp;tr=udp%3A%2F%2Ftracker.coppersurfer.tk%3A6969&amp;tr=udp%3A%2F%2Fexodus.desync.com%3A6969","seeders":1,"leechers":0,"uploader":"zibbik","files":11,"time":1288487771,"description":"Band: Lyzanxia\nAlbum: Locust\nYear: 2010\nGenre: Melodic Thrash Metal\nOrigin: France\nFormat: mp3@CBR320kbps\n &lt;a href=&quot;\nhttp://www.lyzanxia.com/&quot; rel=&quot;nofollow&quot; target=&quot;_NEW&quot;&gt;\nhttp://www.lyzanxia.com/&lt;/a&gt;\n\nTracks:\n1. Prime Thrill 04:26\n2. Underlie 03:37\n3. Separate World 05:30\n4. Light Transition 04:18\n5. Parasitic Growth 03:49\n6. The Clamp 03:38\n7. Mind Tracker 03:13\n8. Hundred-Story Moth 05:05\n9. Tommorow Died 04:24\n10. Subhero Zero 04:39\n11. Father RÃƒÂ¢ 04:54\nTotal playing time 47:33 \n\nCurrent line-up \nDavid Potvin - Guitars, Vocals (Phaze I, One-Way Mirror)\nEguil Voisin - Bass (Reverence (Fra))\nFranck Potvin - Guitars, Vocals (Phaze I, One-Way Mirror)\nClement Decrock - Drums \n","torrent":{"xt":"urn:btih:48be611c499aad9b5830f78b58a2730b7f237dff","amp;dn":"Lyzanxia+-+Locust+%282010%29+%5Bmp3%40320%5D","amp;tr":["udp%3A%2F%2Ftracker.openbittorrent.com%3A80","udp%3A%2F%2Fopen.demonii.com%3A1337","udp%3A%2F%2Ftracker.coppersurfer.tk%3A6969","udp%3A%2F%2Fexodus.desync.com%3A6969"],"infoHash":"48be611c499aad9b5830f78b58a2730b7f237dff","infoHashBuffer":{"type":"Buffer","data":[72,190,97,28,73,154,173,155,88,48,247,139,88,162,115,11,127,35,125,255]},"announce":[],"urlList":[]}}