{"title":"LED ZEPPELIN HAMMER OF THE GODS LIVE 1975 3CD FLAC","uid":11353798,"size":1466878142,"categoryP":"audio","categoryS":"flac","magnet":"?xt=urn:btih:571eb37863633e7ccdb79c41a00e2a7117d31e7d&amp;dn=LED+ZEPPELIN+HAMMER+OF+THE+GODS+LIVE+1975+3CD+FLAC&amp;tr=udp%3A%2F%2Ftracker.openbittorrent.com%3A80&amp;tr=udp%3A%2F%2Fopen.demonii.com%3A1337&amp;tr=udp%3A%2F%2Ftracker.coppersurfer.tk%3A6969&amp;tr=udp%3A%2F%2Fexodus.desync.com%3A6969","seeders":1,"leechers":0,"uploader":"mike0008","files":24,"time":1414920408,"description":"LED ZEPPELIN HAMMER OF THE GODS LIVE 1975 3CD FLAC\n\nCD01 (79:11)\nCD01 01 INTRODUCTION (1975.05.25 Earls Court) 1:51\nCD01 02 ROCK AND ROLL (1975.02.12 New York) 3:43\nCD01 03 SICK AGAIN (1975.03.19 Vancouver) 6:40\nCD01 04 OVER THE HILLS AND FAR AWAY (1975.03.04 Dallas) 7:37\nCD01 05 IN MY TIME OF DYING (1975.02.12 New York) 12:13\nCD01 06 THE SONG REMAINS THE SAME (1975.02.12 New York) 5:28\nCD01 07 THE RAIN SONG (1975.02.12 New York) 8:19\nCD01 08 KASHMIR (1975.02.12 New York) 9:10\nCD01 09 NO QUARTER (1975.03.19 Vancouver) 24:06\n\nCD02 (63:53)\nCD02 01 SINCE I'VE BEEN LOVING YOU (1975.03.27 Los Angeles) 8:01\nCD02 02 TANGERINE (1975.05.24 Earls Court) 5:18\nCD02 03 GOING TO CALIFORNIA (1975.05.25 Earls Court) 4:50\nCD02 04 THAT'S THE WAY (1975.05.25 Earls Court) 6:18\nCD02 05 BRON-Y-AUR STOMP (1975.05.25 Earls Court) 6:05\nCD02 06 TRAMPLED UNDERFOOT (1975.05.25 Earls Court) 9:00\nCD02 07 MOBY DICK (1975.03.19 Vancouver) 24:18\n\nCD03 (78:51)\nCD03 01 DAZED AND CONFUSED (1975.03.19 Vancouver) 39:16\nCD03 02 STAIRWAY TO HEAVEN (1975.05.25 Earls Court) 10:30\nCD03 03 WHOLE LOTTA LOVE/CRUNGE (1975.03.19 Vancouver) 7:58\nCD03 04 BLACK DOG (1975.02.12 New York) 6:26\nCD03 05 HEARTBREAKER (1975.02.12 New York) 9:00\nCD03 06 COMMUNICATION BREAKDOWN (1975.05.25 Earls Court) 5:39\n\nA live 1975 Led Zeppelin compilation I put together some years ago.  I've enjoyed it and thought others might enjoy it as well.  It's more or less merged together to give the impression of a long three hour 45 minute concert.  Mostly using Earls Court '75, New York '75 and Vancouver '75 with a couple other tracks thrown in.  I went with some of the better sounding recordings.\n\nFeel free to share with anyone anytime anywhere.\nSeed if possible. Thanks, Mike","torrent":{"xt":"urn:btih:571eb37863633e7ccdb79c41a00e2a7117d31e7d","amp;dn":"LED+ZEPPELIN+HAMMER+OF+THE+GODS+LIVE+1975+3CD+FLAC","amp;tr":["udp%3A%2F%2Ftracker.openbittorrent.com%3A80","udp%3A%2F%2Fopen.demonii.com%3A1337","udp%3A%2F%2Ftracker.coppersurfer.tk%3A6969","udp%3A%2F%2Fexodus.desync.com%3A6969"],"infoHash":"571eb37863633e7ccdb79c41a00e2a7117d31e7d","infoHashBuffer":{"type":"Buffer","data":[87,30,179,120,99,99,62,124,205,183,156,65,160,14,42,113,23,211,30,125]},"announce":[],"urlList":[]}}