{"title":"007 James Bond The Spy who Loved Me 1977 DvDrip-soagg","uid":4463299,"size":763936674,"categoryP":"video","categoryS":"movies","magnet":"?xt=urn:btih:5752f7fe9830136ca273107219abca3484c79234&amp;dn=007+James+Bond+The+Spy+who+Loved+Me+1977+DvDrip-soagg&amp;tr=udp%3A%2F%2Ftracker.openbittorrent.com%3A80&amp;tr=udp%3A%2F%2Fopen.demonii.com%3A1337&amp;tr=udp%3A%2F%2Ftracker.coppersurfer.tk%3A6969&amp;tr=udp%3A%2F%2Fexodus.desync.com%3A6969","seeders":1,"leechers":1,"uploader":"soagg","files":13,"time":1224799005,"description":"James Bond (007) Collection : 10 The Spy Who Loved Me (1977) Roger Moore\n\n\nPlease seed!!! I can support it for few downloads after that I will stop seeding!!!!\n\nDo write some comments on the quality of the Videos!!!!\n\nSubtitles for English, Swedish, Norwegian, Danish, Finnish, German, Spanish, Polish and Portuguese included!!!\n\nOutline:\nWhen a massive underwater craft abducts U.S. and Russian submarines, global tensions are heightened to the brink of war. In order to find the true culprit, James Bond joins forces with beautiful Russian secret agent Anya Amasaova. Together they follow a trail that leads to Karl Stromberg, a powerful shipping magnate who is implementing a horrific scheme for world domination. Bond struggles to foil the plot, but Stromberg has provided him with the most lethal adversary: Jaws, a seemingly indestructible steel-toothed giant. Agent 007's adventure takes him to the Egyptian pyramids, under the sea and to a mountaintop ski chase that builds to one of the most amazing stunts ever filmed\n\nEnjoy!!!","torrent":{"xt":"urn:btih:5752f7fe9830136ca273107219abca3484c79234","amp;dn":"007+James+Bond+The+Spy+who+Loved+Me+1977+DvDrip-soagg","amp;tr":["udp%3A%2F%2Ftracker.openbittorrent.com%3A80","udp%3A%2F%2Fopen.demonii.com%3A1337","udp%3A%2F%2Ftracker.coppersurfer.tk%3A6969","udp%3A%2F%2Fexodus.desync.com%3A6969"],"infoHash":"5752f7fe9830136ca273107219abca3484c79234","infoHashBuffer":{"type":"Buffer","data":[87,82,247,254,152,48,19,108,162,115,16,114,25,171,202,52,132,199,146,52]},"announce":[],"urlList":[]}}