{"title":"Uncut  - Music (UK) Mar 2012 ","uid":6992327,"size":132262669,"categoryP":"other","categoryS":"e_books","magnet":"?xt=urn:btih:5763d3e873232c6cfc8a8d1482bc9cdab61f97c2&amp;dn=Uncut++-+Music+%28UK%29+Mar+2012+&amp;tr=udp%3A%2F%2Ftracker.openbittorrent.com%3A80&amp;tr=udp%3A%2F%2Fopen.demonii.com%3A1337&amp;tr=udp%3A%2F%2Ftracker.coppersurfer.tk%3A6969&amp;tr=udp%3A%2F%2Fexodus.desync.com%3A6969","seeders":1,"leechers":0,"uploader":"Spetses","files":-1,"time":1327709441,"description":"UNCUT is the UK's most authoritative music and film magazine and every month celebrates the great legends, icons and maverick talents of rock and movies in one brilliant package that embraces both old and new, cult and classic. It is essential reading for anyone with a passion for music and film.","torrent":{"xt":"urn:btih:5763d3e873232c6cfc8a8d1482bc9cdab61f97c2","amp;dn":"Uncut++-+Music+%28UK%29+Mar+2012+","amp;tr":["udp%3A%2F%2Ftracker.openbittorrent.com%3A80","udp%3A%2F%2Fopen.demonii.com%3A1337","udp%3A%2F%2Ftracker.coppersurfer.tk%3A6969","udp%3A%2F%2Fexodus.desync.com%3A6969"],"infoHash":"5763d3e873232c6cfc8a8d1482bc9cdab61f97c2","infoHashBuffer":{"type":"Buffer","data":[87,99,211,232,115,35,44,108,252,138,141,20,130,188,156,218,182,31,151,194]},"announce":[],"urlList":[]}}