{"title":"Don't Tell My Wife I Buttfucked Her Best Friend (DevilsFilm)","uid":8024770,"size":353186601,"categoryP":"porn","categoryS":"movie_clips","magnet":"?xt=urn:btih:61cfff6f8bd9cdc12239fbfe48427570a2b05ef9&amp;dn=Don%27t+Tell+My+Wife+I+Buttfucked+Her+Best+Friend+%28DevilsFilm%29&amp;tr=udp%3A%2F%2Ftracker.openbittorrent.com%3A80&amp;tr=udp%3A%2F%2Fopen.demonii.com%3A1337&amp;tr=udp%3A%2F%2Ftracker.coppersurfer.tk%3A6969&amp;tr=udp%3A%2F%2Fexodus.desync.com%3A6969","seeders":1,"leechers":1,"uploader":"R0thschild","files":-1,"time":1358282033,"description":"Gallery: \n &lt;a href=&quot;\nhttp://hqpdb.com/viewtopic.php?f=11&amp;t=9334&quot; rel=&quot;nofollow&quot; target=&quot;_NEW&quot;&gt;\nhttp://hqpdb.com/viewtopic.php?f=11&amp;t=9334&lt;/a&gt;","torrent":{"xt":"urn:btih:61cfff6f8bd9cdc12239fbfe48427570a2b05ef9","amp;dn":"Don%27t+Tell+My+Wife+I+Buttfucked+Her+Best+Friend+%28DevilsFilm%29","amp;tr":["udp%3A%2F%2Ftracker.openbittorrent.com%3A80","udp%3A%2F%2Fopen.demonii.com%3A1337","udp%3A%2F%2Ftracker.coppersurfer.tk%3A6969","udp%3A%2F%2Fexodus.desync.com%3A6969"],"infoHash":"61cfff6f8bd9cdc12239fbfe48427570a2b05ef9","infoHashBuffer":{"type":"Buffer","data":[97,207,255,111,139,217,205,193,34,57,251,254,72,66,117,112,162,176,94,249]},"announce":[],"urlList":[]}}