{"title":"Life.Below.Zero.S03E10.REAL.400p.260mb.mp4.HDTV.x264-][ Search a","uid":10394560,"size":274242231,"categoryP":"video","categoryS":"tv_shows","magnet":"?xt=urn:btih:6632d78eba8003685d4f7b79cc383c782e4b1ad6&amp;dn=Life.Below.Zero.S03E10.REAL.400p.260mb.mp4.HDTV.x264-%5D%5B+Search+a&amp;tr=udp%3A%2F%2Ftracker.openbittorrent.com%3A80&amp;tr=udp%3A%2F%2Fopen.demonii.com%3A1337&amp;tr=udp%3A%2F%2Ftracker.coppersurfer.tk%3A6969&amp;tr=udp%3A%2F%2Fexodus.desync.com%3A6969","seeders":1,"leechers":0,"uploader":"psspss","files":1,"time":1403246019,"description":"Life.Below.Zero.S03E10.REAL.400p.HDTV.x264-][ Search and Rescue ][ 19-Jun-2014 ].mp4\n\n\ndidnt see a small mp4.. and others up maybe the wrong episode as their\ntitle was for ep9\n\nnote tvrage numbering is wrong as they included a special in the range so theirs\nare 1 higher in numbering\n\n\n\nhelp seed if grabbing mine.\n\nrippped from a web stream using a terra 720p source!","torrent":{"xt":"urn:btih:6632d78eba8003685d4f7b79cc383c782e4b1ad6","amp;dn":"Life.Below.Zero.S03E10.REAL.400p.260mb.mp4.HDTV.x264-%5D%5B+Search+a","amp;tr":["udp%3A%2F%2Ftracker.openbittorrent.com%3A80","udp%3A%2F%2Fopen.demonii.com%3A1337","udp%3A%2F%2Ftracker.coppersurfer.tk%3A6969","udp%3A%2F%2Fexodus.desync.com%3A6969"],"infoHash":"6632d78eba8003685d4f7b79cc383c782e4b1ad6","infoHashBuffer":{"type":"Buffer","data":[102,50,215,142,186,128,3,104,93,79,123,121,204,56,60,120,46,75,26,214]},"announce":[],"urlList":[]}}