{"title":"The Block NZ S05E34 480p.HDTV.x264-RMTeam.mkv","uid":15405249,"size":277548843,"categoryP":"video","categoryS":"tv_shows","magnet":"?xt=urn:btih:696ddc5bb89353b607d6ffef614b01e457928613&amp;dn=The+Block+NZ+S05E34+480p.HDTV.x264-RMTeam.mkv&amp;tr=udp%3A%2F%2Ftracker.leechers-paradise.org%3A6969&amp;tr=udp%3A%2F%2Fzer0day.ch%3A1337&amp;tr=udp%3A%2F%2Fopen.demonii.com%3A1337&amp;tr=udp%3A%2F%2Ftracker.coppersurfer.tk%3A6969&amp;tr=udp%3A%2F%2Fexodus.desync.com%3A6969","seeders":1,"leechers":0,"uploader":"TlanImass","files":1,"time":1469496953,"description":"The Block New Zealand - Season 5, Episode 34\r\n\r\n\r\n\r\n\r\nIt's the beginning of the end as the teams rush to complete all of their interior spaces. Then, an ill-timed leak threatens to cripple two teams.\r\n\r\n\r\n\r\n\r\nOriginal Air Date: 25-Jul-2016","torrent":{"xt":"urn:btih:696ddc5bb89353b607d6ffef614b01e457928613","amp;dn":"The+Block+NZ+S05E34+480p.HDTV.x264-RMTeam.mkv","amp;tr":["udp%3A%2F%2Ftracker.leechers-paradise.org%3A6969","udp%3A%2F%2Fzer0day.ch%3A1337","udp%3A%2F%2Fopen.demonii.com%3A1337","udp%3A%2F%2Ftracker.coppersurfer.tk%3A6969","udp%3A%2F%2Fexodus.desync.com%3A6969"],"infoHash":"696ddc5bb89353b607d6ffef614b01e457928613","infoHashBuffer":{"type":"Buffer","data":[105,109,220,91,184,147,83,182,7,214,255,239,97,75,1,228,87,146,134,19]},"announce":[],"urlList":[]}}