{"title":"Nameless.Gangster.2012.DVDRip.XviD-OCW","uid":7395010,"size":1466753024,"categoryP":"video","categoryS":"movies","magnet":"?xt=urn:btih:7341dc93625155850e2ba00750ab1652c58f00f0&amp;dn=Nameless.Gangster.2012.DVDRip.XviD-OCW&amp;tr=udp%3A%2F%2Ftracker.openbittorrent.com%3A80&amp;tr=udp%3A%2F%2Fopen.demonii.com%3A1337&amp;tr=udp%3A%2F%2Ftracker.coppersurfer.tk%3A6969&amp;tr=udp%3A%2F%2Fexodus.desync.com%3A6969","seeders":1,"leechers":0,"uploader":"maximersk","files":1,"time":1340892325,"description":"Nameless.Gangster.2012.DVDRip.XviD-OCW\n\n\n\n\n\nNameless Gangster (2012) aka Bumchoiwaui junjaeng\nPlot: A corrupted customs officer, Choi Ik-hyeon, faces losing his job. Then, his life turns around as he meets ganster Choi Hyeong-bae who has connection with the Yakuza. They quickly form a partnetship; Hyeong-bae helps Ik-hyeon set up a business with the money from drug trafficking while Ik-hyeon lobbies for his partner Hyeong-bae. As the government declares war on crime, however, their partnership begins to crack.\n &lt;a href=&quot;\nhttp://www.imdb.com/title/tt2082221/&quot; rel=&quot;nofollow&quot; target=&quot;_NEW&quot;&gt;\nhttp://www.imdb.com/title/tt2082221/&lt;/a&gt;\n\nLanguage : JANAPESE\nSub: HC ENGLISH\n\nGenre: Crime | Thriller\niMDB Rating: 8.0/10 from 138 users\nDirector: Jong-bin Yun\nCast: Min-sik Choi and Jung-woo Ha","torrent":{"xt":"urn:btih:7341dc93625155850e2ba00750ab1652c58f00f0","amp;dn":"Nameless.Gangster.2012.DVDRip.XviD-OCW","amp;tr":["udp%3A%2F%2Ftracker.openbittorrent.com%3A80","udp%3A%2F%2Fopen.demonii.com%3A1337","udp%3A%2F%2Ftracker.coppersurfer.tk%3A6969","udp%3A%2F%2Fexodus.desync.com%3A6969"],"infoHash":"7341dc93625155850e2ba00750ab1652c58f00f0","infoHashBuffer":{"type":"Buffer","data":[115,65,220,147,98,81,85,133,14,43,160,7,80,171,22,82,197,143,0,240]},"announce":[],"urlList":[]}}