{"title":"Chuck Berry - Original Chess Classics","uid":5904584,"size":41306112,"categoryP":"audio","categoryS":"music","magnet":"?xt=urn:btih:77f6143d3319ca00798483f4d71c350b78af253a&amp;dn=Chuck+Berry+-+Original+Chess+Classics&amp;tr=udp%3A%2F%2Ftracker.openbittorrent.com%3A80&amp;tr=udp%3A%2F%2Fopen.demonii.com%3A1337&amp;tr=udp%3A%2F%2Ftracker.coppersurfer.tk%3A6969&amp;tr=udp%3A%2F%2Fexodus.desync.com%3A6969","seeders":1,"leechers":0,"uploader":"gibsonman","files":16,"time":1287811360,"description":"Chuck Berry - Original Chess Classics [released 1990] 128bps\n\n01. Roll Over Beethoven\n02. Maybelline\n03. Sweet Little Sixteen\n04. Rock &amp; Roll Music\n05. No Particular Place To Go\n06. Johnny B. Goode\n07. Little Queenie\n08. You Never Can Tell\n09. School Days\n10. Carol\n11. Back In The USA\n12. My Ding-A-Ling\n13. Nadine\n14. Memphis\n15. Brown Eyed Handsome Man\n16. Promised Land","torrent":{"xt":"urn:btih:77f6143d3319ca00798483f4d71c350b78af253a","amp;dn":"Chuck+Berry+-+Original+Chess+Classics","amp;tr":["udp%3A%2F%2Ftracker.openbittorrent.com%3A80","udp%3A%2F%2Fopen.demonii.com%3A1337","udp%3A%2F%2Ftracker.coppersurfer.tk%3A6969","udp%3A%2F%2Fexodus.desync.com%3A6969"],"infoHash":"77f6143d3319ca00798483f4d71c350b78af253a","infoHashBuffer":{"type":"Buffer","data":[119,246,20,61,51,25,202,0,121,132,131,244,215,28,53,11,120,175,37,58]},"announce":[],"urlList":[]}}