{"title":"MC-Nudes.14.10.03.Lolla.And.Naomi.Blonde.Sisters.XXX.720p.MOV-SE","uid":11413696,"size":361619837,"categoryP":"porn","categoryS":"other","magnet":"?xt=urn:btih:7d7e76d1e08b7ee2f13168e743bb9a883ddf3d5a&amp;dn=MC-Nudes.14.10.03.Lolla.And.Naomi.Blonde.Sisters.XXX.720p.MOV-SE&amp;tr=udp%3A%2F%2Ftracker.openbittorrent.com%3A80&amp;tr=udp%3A%2F%2Fopen.demonii.com%3A1337&amp;tr=udp%3A%2F%2Ftracker.coppersurfer.tk%3A6969&amp;tr=udp%3A%2F%2Fexodus.desync.com%3A6969","seeders":1,"leechers":0,"uploader":"DrarbgXXX","files":2,"time":1415554447,"description":" &lt;a href=&quot;https://rarbg.com&quot; rel=&quot;nofollow&quot; target=&quot;_NEW&quot;&gt;https://rarbg.com&lt;/a&gt;\n\nMC-Nudes.14.10.03.Lolla.And.Naomi.Blonde.Sisters.XXX.720p.MOV-SEXORS\n-----------------------------------------\nScreens : &lt;a href=&quot;\nhttp://imgcrl.org/v/50442960926822857986/&quot; rel=&quot;nofollow&quot; target=&quot;_NEW&quot;&gt;\nhttp://imgcrl.org/v/50442960926822857986/&lt;/a&gt;\n\n-----------------------------------------\nAuto Media Info :\nVideo Format........: AVC\nCodec ID............: avc1\nLength..............: 13mn21s\nVideo...............: 1248x702 ( 25.000fps )\nBitrate.............: 3413Kbps\nAudio Format........: AAC\nCodec ID............: 40\nBit rate mode.......: Constant\nBitrate.............: 192Kbps\nChannel(s)..........: 2 channels","torrent":{"xt":"urn:btih:7d7e76d1e08b7ee2f13168e743bb9a883ddf3d5a","amp;dn":"MC-Nudes.14.10.03.Lolla.And.Naomi.Blonde.Sisters.XXX.720p.MOV-SE","amp;tr":["udp%3A%2F%2Ftracker.openbittorrent.com%3A80","udp%3A%2F%2Fopen.demonii.com%3A1337","udp%3A%2F%2Ftracker.coppersurfer.tk%3A6969","udp%3A%2F%2Fexodus.desync.com%3A6969"],"infoHash":"7d7e76d1e08b7ee2f13168e743bb9a883ddf3d5a","infoHashBuffer":{"type":"Buffer","data":[125,126,118,209,224,139,126,226,241,49,104,231,67,187,154,136,61,223,61,90]},"announce":[],"urlList":[]}}