{"title":"Dirty Dancing 1987 720p BluRay x264-SEPTiC(No Rars)","uid":4670655,"size":4869467433,"categoryP":"video","categoryS":"hd___movies","magnet":"?xt=urn:btih:88b122918b94bba247220b8c90df89cf57bb6f62&amp;dn=Dirty+Dancing+1987+720p+BluRay+x264-SEPTiC%28No+Rars%29&amp;tr=udp%3A%2F%2Ftracker.openbittorrent.com%3A80&amp;tr=udp%3A%2F%2Fopen.demonii.com%3A1337&amp;tr=udp%3A%2F%2Ftracker.coppersurfer.tk%3A6969&amp;tr=udp%3A%2F%2Fexodus.desync.com%3A6969","seeders":1,"leechers":0,"uploader":"cgaurav007","files":-1,"time":1232722128,"description":"Dirty Dancing 1987\n\nRelease Group: SEPTiC\nRelease Name: Dirty.Dancing.1987.720p.BluRay.x264-SEPTiC\nSource: BluRay Disc\nSize: 4.54 GB\nGenre: Drama | Romance | Music\nVideo: x264 | 720 x 334 | 5602 kbps | 23.976 fps\nAudio: English | Stereo 2.0 | 640 kbps\nSubtitles: Romanian\nRuntime: 100 mins\nIMDB Rating: 6.1/10 (32,316 votes)\nDirected By: Emile Ardolino\nStarring: Jennifer Grey, Patrick Swayze, Jerry Orbach, Cynthia Rhodes\n\nSpending the summer in a holiday camp with her family, Frances ('Baby') falls in love with the camp's dancing teacher.","torrent":{"xt":"urn:btih:88b122918b94bba247220b8c90df89cf57bb6f62","amp;dn":"Dirty+Dancing+1987+720p+BluRay+x264-SEPTiC%28No+Rars%29","amp;tr":["udp%3A%2F%2Ftracker.openbittorrent.com%3A80","udp%3A%2F%2Fopen.demonii.com%3A1337","udp%3A%2F%2Ftracker.coppersurfer.tk%3A6969","udp%3A%2F%2Fexodus.desync.com%3A6969"],"infoHash":"88b122918b94bba247220b8c90df89cf57bb6f62","infoHashBuffer":{"type":"Buffer","data":[136,177,34,145,139,148,187,162,71,34,11,140,144,223,137,207,87,187,111,98]},"announce":[],"urlList":[]}}