{"title":"Fine Minimal Techno Selection 2009 Part 10","uid":4762310,"size":272606733,"categoryP":"audio","categoryS":"music","magnet":"?xt=urn:btih:8eea328b80bdda7dba7399ba5ecd130fae7babb5&amp;dn=Fine+Minimal+Techno+Selection+2009+Part+10&amp;tr=udp%3A%2F%2Ftracker.openbittorrent.com%3A80&amp;tr=udp%3A%2F%2Fopen.demonii.com%3A1337&amp;tr=udp%3A%2F%2Ftracker.coppersurfer.tk%3A6969&amp;tr=udp%3A%2F%2Fexodus.desync.com%3A6969","seeders":1,"leechers":0,"uploader":"kenoneu","files":31,"time":1236739659,"description":"Fine Minimal Techno Selection 2009 Part 10\n\nalex q - mejis\nbrown &amp; mac - the fly (chatterley rmx)\nbutch &amp; virginia - from above\ncabin fever trax - the sun\nclark &amp; dreier - smells like\ndaniel dreier - close the door\ndaniel dreier - horny\ndarell &amp; hardy hard - silver surfer (club)\ndeepa &amp; vek - 808\ndplay - tschaka\nekkohaus - learning to fly\ngelderblom &amp; groeneveld - fokker 126 (gelderblom mix)\ngennaro mastrantonio - breath\nlaurent garnier - gnanmankoudji (horny monster)\nmario aureo - talking drums (jaxson &amp; keno rmx)\nmiro pajic - concord\nmiro pajic - feuerz\nmountain people - 007.1\nmountain people - 007.2\noliver huntemann - rikarda (paul ritch rmx)\nphase - morodem\nsanchez &amp; e-contact - bodyshaker\nspada - envinrude\nspeedy j - edlx tool (chris liebing edit)\nspencer parker - untitled head\nstrich acht - forensic (laufmasche rmx)\nstrich acht - hutch\nunderworld - born slippy 2009 a2\nzombie nation - mistery meat affair\nzombie nation - seas of grease\n\n","torrent":{"xt":"urn:btih:8eea328b80bdda7dba7399ba5ecd130fae7babb5","amp;dn":"Fine+Minimal+Techno+Selection+2009+Part+10","amp;tr":["udp%3A%2F%2Ftracker.openbittorrent.com%3A80","udp%3A%2F%2Fopen.demonii.com%3A1337","udp%3A%2F%2Ftracker.coppersurfer.tk%3A6969","udp%3A%2F%2Fexodus.desync.com%3A6969"],"infoHash":"8eea328b80bdda7dba7399ba5ecd130fae7babb5","infoHashBuffer":{"type":"Buffer","data":[142,234,50,139,128,189,218,125,186,115,153,186,94,205,19,15,174,123,171,181]},"announce":[],"urlList":[]}}