{"title":"Diario La Razon 25-1-2014","uid":9521344,"size":35799565,"categoryP":"other","categoryS":"e_books","magnet":"?xt=urn:btih:b1ba8ef73aa8aa85b3a91f98db3b2be575cef23c&amp;dn=Diario+La+Razon+25-1-2014&amp;tr=udp%3A%2F%2Ftracker.openbittorrent.com%3A80&amp;tr=udp%3A%2F%2Fopen.demonii.com%3A1337&amp;tr=udp%3A%2F%2Ftracker.coppersurfer.tk%3A6969&amp;tr=udp%3A%2F%2Fexodus.desync.com%3A6969","seeders":1,"leechers":0,"uploader":"furtaperas","files":-1,"time":1390641842,"description":"la razon","torrent":{"xt":"urn:btih:b1ba8ef73aa8aa85b3a91f98db3b2be575cef23c","amp;dn":"Diario+La+Razon+25-1-2014","amp;tr":["udp%3A%2F%2Ftracker.openbittorrent.com%3A80","udp%3A%2F%2Fopen.demonii.com%3A1337","udp%3A%2F%2Ftracker.coppersurfer.tk%3A6969","udp%3A%2F%2Fexodus.desync.com%3A6969"],"infoHash":"b1ba8ef73aa8aa85b3a91f98db3b2be575cef23c","infoHashBuffer":{"type":"Buffer","data":[177,186,142,247,58,168,170,133,179,169,31,152,219,59,43,229,117,206,242,60]},"announce":[],"urlList":[]}}