{"title":"ScoreHD - [Lily Madison] (2014)","uid":9809863,"size":339314006,"categoryP":"porn","categoryS":"movie_clips","magnet":"?xt=urn:btih:c44e5d0fbb1b8c698caff61c7662922bbb45d1b5&amp;dn=ScoreHD+-+%5BLily+Madison%5D+%282014%29&amp;tr=udp%3A%2F%2Ftracker.openbittorrent.com%3A80&amp;tr=udp%3A%2F%2Fopen.demonii.com%3A1337&amp;tr=udp%3A%2F%2Ftracker.coppersurfer.tk%3A6969&amp;tr=udp%3A%2F%2Fexodus.desync.com%3A6969","seeders":1,"leechers":0,"uploader":"makintos13","files":1,"time":1395508181,"description":"screen:\n &lt;a href=&quot;\nhttp://imgfun.biz/img-532db495ef10d.html&quot; rel=&quot;nofollow&quot; target=&quot;_NEW&quot;&gt;\nhttp://imgfun.biz/img-532db495ef10d.html&lt;/a&gt;","torrent":{"xt":"urn:btih:c44e5d0fbb1b8c698caff61c7662922bbb45d1b5","amp;dn":"ScoreHD+-+%5BLily+Madison%5D+%282014%29","amp;tr":["udp%3A%2F%2Ftracker.openbittorrent.com%3A80","udp%3A%2F%2Fopen.demonii.com%3A1337","udp%3A%2F%2Ftracker.coppersurfer.tk%3A6969","udp%3A%2F%2Fexodus.desync.com%3A6969"],"infoHash":"c44e5d0fbb1b8c698caff61c7662922bbb45d1b5","infoHashBuffer":{"type":"Buffer","data":[196,78,93,15,187,27,140,105,140,175,246,28,118,98,146,43,187,69,209,181]},"announce":[],"urlList":[]}}