{"title":"Yes-R - Fashion (2012) DutchReleaseTeam","uid":7677887,"size":89140427,"categoryP":"audio","categoryS":"other","magnet":"?xt=urn:btih:cc47e9e379bf937f66840beed894ab9acc58f5cb&amp;dn=Yes-R+-+Fashion+%282012%29+DutchReleaseTeam&amp;tr=udp%3A%2F%2Ftracker.openbittorrent.com%3A80&amp;tr=udp%3A%2F%2Fopen.demonii.com%3A1337&amp;tr=udp%3A%2F%2Ftracker.coppersurfer.tk%3A6969&amp;tr=udp%3A%2F%2Fexodus.desync.com%3A6969","seeders":1,"leechers":0,"uploader":"Boobin16","files":-1,"time":1348751888,"description":"\n\n Genre: Rap/Hip Hop\n Extensie: Mp3 \n Bitrate: Variabel\n Cover: Front\n Jaar: 2012\n\n \nTracklist\n\n 1. Fashion \n 2. All About The Fashion Feat. Brace \n 3. Zusjes \n 4. Heimwee Feat. Angela Groothuizen \n 5. Als Er Geen Morgen Was \n 6. Bloedend Hart Feat. Ruth Jacott \n 7. I Got It (Skit) \n 8. Ik Ben De Shit \n 9. Fluister Feat. Ruby Prophet \n 10. Spiegel Aan De Wand \n 11. Late Night Show \n 12. Ruimtereis Feat. Will-M \n 13. Tel Ik Nog Mee Feat. Rolf Sanchez \n 14. De Wereld Rond\n\n\nDeze CD wordt u aangeboden door het DutchReleaseTeam.\nVoor de reviews van de nieuwste films, muziek, series , games etc.\nKom eens langs op  &lt;a href=&quot; http://www.hetmultimediacafe.be/&quot; rel=&quot;nofollow&quot; target=&quot;_NEW&quot;&gt; http://www.hetmultimediacafe.be/&lt;/a&gt;","torrent":{"xt":"urn:btih:cc47e9e379bf937f66840beed894ab9acc58f5cb","amp;dn":"Yes-R+-+Fashion+%282012%29+DutchReleaseTeam","amp;tr":["udp%3A%2F%2Ftracker.openbittorrent.com%3A80","udp%3A%2F%2Fopen.demonii.com%3A1337","udp%3A%2F%2Ftracker.coppersurfer.tk%3A6969","udp%3A%2F%2Fexodus.desync.com%3A6969"],"infoHash":"cc47e9e379bf937f66840beed894ab9acc58f5cb","infoHashBuffer":{"type":"Buffer","data":[204,71,233,227,121,191,147,127,102,132,11,238,216,148,171,154,204,88,245,203]},"announce":[],"urlList":[]}}