{"title":"Carola - Hunger (remix) - Italian 12 inch (1984)","uid":5787840,"size":17972176,"categoryP":"audio","categoryS":"music","magnet":"?xt=urn:btih:d454346fe5a27579891ca93870c05dd323937d66&amp;dn=Carola+-+Hunger+%28remix%29+-+Italian+12+inch+%281984%29&amp;tr=udp%3A%2F%2Ftracker.openbittorrent.com%3A80&amp;tr=udp%3A%2F%2Fopen.demonii.com%3A1337&amp;tr=udp%3A%2F%2Ftracker.coppersurfer.tk%3A6969&amp;tr=udp%3A%2F%2Fexodus.desync.com%3A6969","seeders":1,"leechers":0,"uploader":"AnotherStranger","files":-1,"time":1282716673,"description":"Swedish artist Carola HÃƒÂ¤ggkvist's one and only Italian 12 inch, some fantastic 80's music:\n\nA - Hunger (remix - disco version)\nB - Hunger (remix - other version)\n\n~210kbps VBR MP3, LAME 3.98, Recorded from 12&quot; vinyl","torrent":{"xt":"urn:btih:d454346fe5a27579891ca93870c05dd323937d66","amp;dn":"Carola+-+Hunger+%28remix%29+-+Italian+12+inch+%281984%29","amp;tr":["udp%3A%2F%2Ftracker.openbittorrent.com%3A80","udp%3A%2F%2Fopen.demonii.com%3A1337","udp%3A%2F%2Ftracker.coppersurfer.tk%3A6969","udp%3A%2F%2Fexodus.desync.com%3A6969"],"infoHash":"d454346fe5a27579891ca93870c05dd323937d66","infoHashBuffer":{"type":"Buffer","data":[212,84,52,111,229,162,117,121,137,28,169,56,112,192,93,211,35,147,125,102]},"announce":[],"urlList":[]}}