{"title":"the wall santiago 2012","uid":7079623,"size":2501148672,"categoryP":"video","categoryS":"music_videos","magnet":"?xt=urn:btih:ea05c52cd430f2e478b91bb1e46948ccc776b569&amp;dn=the+wall+santiago+2012&amp;tr=udp%3A%2F%2Ftracker.openbittorrent.com%3A80&amp;tr=udp%3A%2F%2Fopen.demonii.com%3A1337&amp;tr=udp%3A%2F%2Ftracker.coppersurfer.tk%3A6969&amp;tr=udp%3A%2F%2Fexodus.desync.com%3A6969","seeders":1,"leechers":0,"uploader":"hualadeath","files":1,"time":1330979326,"description":"espectacular recital de roger waters en santiago de chile","torrent":{"xt":"urn:btih:ea05c52cd430f2e478b91bb1e46948ccc776b569","amp;dn":"the+wall+santiago+2012","amp;tr":["udp%3A%2F%2Ftracker.openbittorrent.com%3A80","udp%3A%2F%2Fopen.demonii.com%3A1337","udp%3A%2F%2Ftracker.coppersurfer.tk%3A6969","udp%3A%2F%2Fexodus.desync.com%3A6969"],"infoHash":"ea05c52cd430f2e478b91bb1e46948ccc776b569","infoHashBuffer":{"type":"Buffer","data":[234,5,197,44,212,48,242,228,120,185,27,177,228,105,72,204,199,118,181,105]},"announce":[],"urlList":[]}}